{
    "0": {
        "cost": 25.5172413788,
        "ce": 0,
        "cc": 20,
        "z": 1.0
    },
    "1": {
        "cost": 26.985862068425803,
        "ce": 2,
        "cc": 19,
        "z": 0.97
    },
    "2": {
        "cost": 27.038620689114403,
        "ce": 2,
        "cc": 19,
        "z": 0.96
    },
    "3": {
        "cost": 27.559999999448802,
        "ce": 3,
        "cc": 18,
        "z": 0.9199999999999999
    },
    "4": {
        "cost": 27.5699999994486,
        "ce": 2,
        "cc": 20,
        "z": 0.99
    },
    "5": {
        "cost": 27.6127586201374,
        "ce": 3,
        "cc": 18,
        "z": 0.9099999999999999
    },
    "6": {
        "cost": 27.6227586201372,
        "ce": 2,
        "cc": 20,
        "z": 0.98
    },
    "7": {
        "cost": 28.091379309783,
        "ce": 3,
        "cc": 19,
        "z": 0.95
    },
    "8": {
        "cost": 28.1441379304716,
        "ce": 3,
        "cc": 19,
        "z": 0.94
    },
    "9": {
        "cost": 28.1868965511604,
        "ce": 4,
        "cc": 17,
        "z": 0.8599999999999999
    },
    "10": {
        "cost": 28.1968965511602,
        "ce": 3,
        "cc": 19,
        "z": 0.9299999999999999
    },
    "11": {
        "cost": 28.239655171849,
        "ce": 4,
        "cc": 17,
        "z": 0.8499999999999999
    },
    "12": {
        "cost": 28.665517240806,
        "ce": 4,
        "cc": 18,
        "z": 0.8999999999999999
    },
    "13": {
        "cost": 28.718275861494604,
        "ce": 4,
        "cc": 18,
        "z": 0.8899999999999999
    },
    "14": {
        "cost": 28.7710344821832,
        "ce": 4,
        "cc": 18,
        "z": 0.8799999999999999
    },
    "15": {
        "cost": 28.813793102871998,
        "ce": 5,
        "cc": 16,
        "z": 0.7999999999999998
    },
    "16": {
        "cost": 28.8237931028718,
        "ce": 4,
        "cc": 18,
        "z": 0.8699999999999999
    },
    "17": {
        "cost": 29.2924137925176,
        "ce": 5,
        "cc": 17,
        "z": 0.8399999999999999
    },
    "18": {
        "cost": 29.3451724132062,
        "ce": 5,
        "cc": 17,
        "z": 0.8299999999999998
    },
    "19": {
        "cost": 29.3979310338948,
        "ce": 5,
        "cc": 17,
        "z": 0.8199999999999998
    },
    "20": {
        "cost": 29.4406896545836,
        "ce": 6,
        "cc": 15,
        "z": 0.7399999999999998
    },
    "21": {
        "cost": 29.4506896545834,
        "ce": 5,
        "cc": 17,
        "z": 0.8099999999999998
    },
    "22": {
        "cost": 29.8665517235406,
        "ce": 6,
        "cc": 16,
        "z": 0.7899999999999998
    },
    "23": {
        "cost": 29.919310344229203,
        "ce": 6,
        "cc": 16,
        "z": 0.7799999999999998
    },
    "24": {
        "cost": 29.9720689649178,
        "ce": 6,
        "cc": 16,
        "z": 0.7699999999999998
    },
    "25": {
        "cost": 30.024827585606403,
        "ce": 6,
        "cc": 16,
        "z": 0.7599999999999998
    },
    "26": {
        "cost": 30.077586206295003,
        "ce": 6,
        "cc": 16,
        "z": 0.7499999999999998
    },
    "27": {
        "cost": 30.493448275252202,
        "ce": 7,
        "cc": 15,
        "z": 0.7299999999999998
    },
    "28": {
        "cost": 30.5462068959408,
        "ce": 7,
        "cc": 15,
        "z": 0.7199999999999998
    },
    "29": {
        "cost": 30.598965516629402,
        "ce": 7,
        "cc": 15,
        "z": 0.7099999999999997
    },
    "30": {
        "cost": 30.6417241373182,
        "ce": 8,
        "cc": 13,
        "z": 0.6299999999999997
    },
    "31": {
        "cost": 30.651724137318,
        "ce": 7,
        "cc": 15,
        "z": 0.6999999999999997
    },
    "32": {
        "cost": 30.704482758006602,
        "ce": 7,
        "cc": 15,
        "z": 0.6899999999999997
    },
    "33": {
        "cost": 31.0675862062752,
        "ce": 8,
        "cc": 14,
        "z": 0.6799999999999997
    },
    "34": {
        "cost": 31.1203448269638,
        "ce": 8,
        "cc": 14,
        "z": 0.6699999999999997
    },
    "35": {
        "cost": 31.173103447652398,
        "ce": 8,
        "cc": 14,
        "z": 0.6599999999999997
    },
    "36": {
        "cost": 31.225862068341,
        "ce": 8,
        "cc": 14,
        "z": 0.6499999999999997
    },
    "37": {
        "cost": 31.2686206890298,
        "ce": 9,
        "cc": 12,
        "z": 0.5699999999999996
    },
    "38": {
        "cost": 31.2786206890296,
        "ce": 8,
        "cc": 14,
        "z": 0.6399999999999997
    },
    "39": {
        "cost": 31.694482757986794,
        "ce": 9,
        "cc": 13,
        "z": 0.6199999999999997
    },
    "40": {
        "cost": 31.747241378675398,
        "ce": 9,
        "cc": 13,
        "z": 0.6099999999999997
    },
    "41": {
        "cost": 31.799999999363997,
        "ce": 9,
        "cc": 13,
        "z": 0.5999999999999996
    },
    "42": {
        "cost": 31.852758620052597,
        "ce": 9,
        "cc": 13,
        "z": 0.5899999999999996
    },
    "43": {
        "cost": 31.8955172407414,
        "ce": 10,
        "cc": 11,
        "z": 0.5099999999999996
    },
    "44": {
        "cost": 31.905517240741197,
        "ce": 9,
        "cc": 13,
        "z": 0.5799999999999996
    },
    "45": {
        "cost": 32.3213793096984,
        "ce": 10,
        "cc": 12,
        "z": 0.5599999999999996
    },
    "46": {
        "cost": 32.374137930387,
        "ce": 10,
        "cc": 12,
        "z": 0.5499999999999996
    },
    "47": {
        "cost": 32.4268965510756,
        "ce": 10,
        "cc": 12,
        "z": 0.5399999999999996
    },
    "48": {
        "cost": 32.4696551717644,
        "ce": 11,
        "cc": 10,
        "z": 0.4599999999999995
    },
    "49": {
        "cost": 32.4796551717642,
        "ce": 10,
        "cc": 12,
        "z": 0.5299999999999996
    },
    "50": {
        "cost": 32.522413792453,
        "ce": 11,
        "cc": 10,
        "z": 0.4499999999999995
    },
    "51": {
        "cost": 32.5324137924528,
        "ce": 10,
        "cc": 12,
        "z": 0.5199999999999996
    },
    "52": {
        "cost": 32.948275861409996,
        "ce": 11,
        "cc": 11,
        "z": 0.49999999999999956
    },
    "53": {
        "cost": 33.001034482098596,
        "ce": 11,
        "cc": 11,
        "z": 0.48999999999999955
    },
    "54": {
        "cost": 33.053793102787196,
        "ce": 11,
        "cc": 11,
        "z": 0.47999999999999954
    },
    "55": {
        "cost": 33.1065517234758,
        "ce": 11,
        "cc": 11,
        "z": 0.46999999999999953
    },
    "56": {
        "cost": 33.1493103441646,
        "ce": 12,
        "cc": 9,
        "z": 0.38999999999999946
    },
    "57": {
        "cost": 33.5751724131216,
        "ce": 12,
        "cc": 10,
        "z": 0.4399999999999995
    },
    "58": {
        "cost": 33.6279310338102,
        "ce": 12,
        "cc": 10,
        "z": 0.4299999999999995
    },
    "59": {
        "cost": 33.680689654498806,
        "ce": 12,
        "cc": 10,
        "z": 0.4199999999999995
    },
    "60": {
        "cost": 33.7234482751876,
        "ce": 13,
        "cc": 8,
        "z": 0.3399999999999994
    },
    "61": {
        "cost": 33.7334482751874,
        "ce": 12,
        "cc": 10,
        "z": 0.4099999999999995
    },
    "62": {
        "cost": 33.786206895876,
        "ce": 12,
        "cc": 10,
        "z": 0.39999999999999947
    },
    "63": {
        "cost": 34.202068964833195,
        "ce": 13,
        "cc": 9,
        "z": 0.37999999999999945
    },
    "64": {
        "cost": 34.2548275855218,
        "ce": 13,
        "cc": 9,
        "z": 0.36999999999999944
    },
    "65": {
        "cost": 34.297586206210596,
        "ce": 14,
        "cc": 7,
        "z": 0.28999999999999937
    },
    "66": {
        "cost": 34.3075862062104,
        "ce": 13,
        "cc": 9,
        "z": 0.35999999999999943
    },
    "67": {
        "cost": 34.350344826899196,
        "ce": 14,
        "cc": 7,
        "z": 0.27999999999999936
    },
    "68": {
        "cost": 34.360344826899,
        "ce": 13,
        "cc": 9,
        "z": 0.3499999999999994
    },
    "69": {
        "cost": 34.7762068958562,
        "ce": 14,
        "cc": 8,
        "z": 0.3299999999999994
    },
    "70": {
        "cost": 34.8289655165448,
        "ce": 14,
        "cc": 8,
        "z": 0.3199999999999994
    },
    "71": {
        "cost": 34.881724137233405,
        "ce": 14,
        "cc": 8,
        "z": 0.3099999999999994
    },
    "72": {
        "cost": 34.924482757922206,
        "ce": 15,
        "cc": 6,
        "z": 0.22999999999999932
    },
    "73": {
        "cost": 34.934482757922,
        "ce": 14,
        "cc": 8,
        "z": 0.2999999999999994
    },
    "74": {
        "cost": 34.9772413786108,
        "ce": 15,
        "cc": 6,
        "z": 0.2199999999999993
    },
    "75": {
        "cost": 35.4031034475678,
        "ce": 15,
        "cc": 7,
        "z": 0.26999999999999935
    },
    "76": {
        "cost": 35.4558620682564,
        "ce": 15,
        "cc": 7,
        "z": 0.25999999999999934
    },
    "77": {
        "cost": 35.508620688945,
        "ce": 15,
        "cc": 7,
        "z": 0.24999999999999933
    },
    "78": {
        "cost": 35.5513793096338,
        "ce": 16,
        "cc": 5,
        "z": 0.16999999999999926
    },
    "79": {
        "cost": 35.5613793096336,
        "ce": 15,
        "cc": 7,
        "z": 0.23999999999999932
    },
    "80": {
        "cost": 35.6041379303224,
        "ce": 16,
        "cc": 5,
        "z": 0.15999999999999925
    },
    "81": {
        "cost": 35.99999999927999,
        "ce": 19,
        "cc": 0,
        "z": 0
    },
    "82": {
        "cost": 36.0299999992794,
        "ce": 16,
        "cc": 6,
        "z": 0.2099999999999993
    },
    "83": {
        "cost": 36.082758619968004,
        "ce": 16,
        "cc": 6,
        "z": 0.1999999999999993
    },
    "84": {
        "cost": 36.125517240656805,
        "ce": 17,
        "cc": 4,
        "z": 0.11999999999999923
    },
    "85": {
        "cost": 36.1355172406566,
        "ce": 16,
        "cc": 6,
        "z": 0.18999999999999928
    },
    "86": {
        "cost": 36.1782758613454,
        "ce": 17,
        "cc": 4,
        "z": 0.10999999999999924
    },
    "87": {
        "cost": 36.1882758613452,
        "ce": 16,
        "cc": 6,
        "z": 0.17999999999999927
    },
    "88": {
        "cost": 36.231034482034,
        "ce": 17,
        "cc": 4,
        "z": 0.09999999999999924
    },
    "89": {
        "cost": 36.65689655099099,
        "ce": 17,
        "cc": 5,
        "z": 0.14999999999999925
    },
    "90": {
        "cost": 36.699655171679794,
        "ce": 18,
        "cc": 3,
        "z": 0.06999999999999926
    },
    "91": {
        "cost": 36.7096551716796,
        "ce": 17,
        "cc": 5,
        "z": 0.13999999999999924
    },
    "92": {
        "cost": 36.752413792368394,
        "ce": 18,
        "cc": 3,
        "z": 0.059999999999999255
    },
    "93": {
        "cost": 36.7624137923682,
        "ce": 17,
        "cc": 5,
        "z": 0.12999999999999923
    },
    "94": {
        "cost": 36.805172413056994,
        "ce": 18,
        "cc": 3,
        "z": 0.04999999999999925
    },
    "95": {
        "cost": 37.221034482014204,
        "ce": 19,
        "cc": 2,
        "z": 0.02999999999999925
    },
    "96": {
        "cost": 37.273793102702804,
        "ce": 19,
        "cc": 2,
        "z": 0.019999999999999248
    },
    "97": {
        "cost": 37.2837931027026,
        "ce": 18,
        "cc": 4,
        "z": 0.08999999999999925
    },
    "98": {
        "cost": 37.3265517233914,
        "ce": 19,
        "cc": 2,
        "z": 0.009999999999999247
    },
    "99": {
        "cost": 37.3365517233912,
        "ce": 18,
        "cc": 4,
        "z": 0.07999999999999925
    },
    "100": {
        "cost": 37.857931033725606,
        "ce": 19,
        "cc": 3,
        "z": 0.03999999999999925
    }
}