{
    "0": {
        "cost": 21.379310344399997,
        "ce": 0,
        "cc": 17,
        "z": 1.0
    },
    "1": {
        "cost": 22.819999999543597,
        "ce": 2,
        "cc": 16,
        "z": 0.97
    },
    "2": {
        "cost": 22.8634482754048,
        "ce": 2,
        "cc": 16,
        "z": 0.96
    },
    "3": {
        "cost": 23.422758620221195,
        "ce": 2,
        "cc": 17,
        "z": 0.99
    },
    "4": {
        "cost": 23.434482758152,
        "ce": 3,
        "cc": 15,
        "z": 0.8999999999999999
    },
    "5": {
        "cost": 23.466206896082397,
        "ce": 2,
        "cc": 17,
        "z": 0.98
    },
    "6": {
        "cost": 23.906896551246,
        "ce": 3,
        "cc": 16,
        "z": 0.95
    },
    "7": {
        "cost": 23.950344827107198,
        "ce": 3,
        "cc": 16,
        "z": 0.94
    },
    "8": {
        "cost": 23.993793102968397,
        "ce": 3,
        "cc": 16,
        "z": 0.9299999999999999
    },
    "9": {
        "cost": 24.0372413788296,
        "ce": 3,
        "cc": 16,
        "z": 0.9199999999999999
    },
    "10": {
        "cost": 24.0806896546908,
        "ce": 3,
        "cc": 16,
        "z": 0.9099999999999999
    },
    "11": {
        "cost": 24.477931033993197,
        "ce": 4,
        "cc": 15,
        "z": 0.8899999999999999
    },
    "12": {
        "cost": 24.521379309854396,
        "ce": 4,
        "cc": 15,
        "z": 0.8799999999999999
    },
    "13": {
        "cost": 24.564827585715598,
        "ce": 4,
        "cc": 15,
        "z": 0.8699999999999999
    },
    "14": {
        "cost": 24.6082758615768,
        "ce": 4,
        "cc": 15,
        "z": 0.8599999999999999
    },
    "15": {
        "cost": 24.651724137438002,
        "ce": 4,
        "cc": 15,
        "z": 0.8499999999999999
    },
    "16": {
        "cost": 24.695172413299197,
        "ce": 4,
        "cc": 15,
        "z": 0.8399999999999999
    },
    "17": {
        "cost": 25.0489655167404,
        "ce": 5,
        "cc": 14,
        "z": 0.8299999999999998
    },
    "18": {
        "cost": 25.092413792601597,
        "ce": 5,
        "cc": 14,
        "z": 0.8199999999999998
    },
    "19": {
        "cost": 25.135862068462796,
        "ce": 5,
        "cc": 14,
        "z": 0.8099999999999998
    },
    "20": {
        "cost": 25.179310344323998,
        "ce": 5,
        "cc": 14,
        "z": 0.7999999999999998
    },
    "21": {
        "cost": 25.222758620185196,
        "ce": 5,
        "cc": 14,
        "z": 0.7899999999999998
    },
    "22": {
        "cost": 25.266206896046395,
        "ce": 5,
        "cc": 14,
        "z": 0.7799999999999998
    },
    "23": {
        "cost": 25.309655171907597,
        "ce": 5,
        "cc": 14,
        "z": 0.7699999999999998
    },
    "24": {
        "cost": 25.6634482753488,
        "ce": 6,
        "cc": 13,
        "z": 0.7599999999999998
    },
    "25": {
        "cost": 25.706896551209994,
        "ce": 6,
        "cc": 13,
        "z": 0.7499999999999998
    },
    "26": {
        "cost": 25.750344827071196,
        "ce": 6,
        "cc": 13,
        "z": 0.7399999999999998
    },
    "27": {
        "cost": 25.793793102932398,
        "ce": 6,
        "cc": 13,
        "z": 0.7299999999999998
    },
    "28": {
        "cost": 25.8372413787936,
        "ce": 6,
        "cc": 13,
        "z": 0.7199999999999998
    },
    "29": {
        "cost": 25.880689654654798,
        "ce": 6,
        "cc": 13,
        "z": 0.7099999999999997
    },
    "30": {
        "cost": 25.924137930515997,
        "ce": 6,
        "cc": 13,
        "z": 0.6999999999999997
    },
    "31": {
        "cost": 26.277931033957195,
        "ce": 7,
        "cc": 12,
        "z": 0.6899999999999997
    },
    "32": {
        "cost": 26.321379309818397,
        "ce": 7,
        "cc": 12,
        "z": 0.6799999999999997
    },
    "33": {
        "cost": 26.3648275856796,
        "ce": 7,
        "cc": 12,
        "z": 0.6699999999999997
    },
    "34": {
        "cost": 26.408275861540798,
        "ce": 7,
        "cc": 12,
        "z": 0.6599999999999997
    },
    "35": {
        "cost": 26.451724137401996,
        "ce": 7,
        "cc": 12,
        "z": 0.6499999999999997
    },
    "36": {
        "cost": 26.463448275332794,
        "ce": 8,
        "cc": 10,
        "z": 0.5599999999999996
    },
    "37": {
        "cost": 26.495172413263198,
        "ce": 7,
        "cc": 12,
        "z": 0.6399999999999997
    },
    "38": {
        "cost": 26.538620689124397,
        "ce": 7,
        "cc": 12,
        "z": 0.6299999999999997
    },
    "39": {
        "cost": 26.8924137925656,
        "ce": 8,
        "cc": 11,
        "z": 0.6199999999999997
    },
    "40": {
        "cost": 26.935862068426797,
        "ce": 8,
        "cc": 11,
        "z": 0.6099999999999997
    },
    "41": {
        "cost": 26.979310344288,
        "ce": 8,
        "cc": 11,
        "z": 0.5999999999999996
    },
    "42": {
        "cost": 27.022758620149197,
        "ce": 8,
        "cc": 11,
        "z": 0.5899999999999996
    },
    "43": {
        "cost": 27.066206896010396,
        "ce": 8,
        "cc": 11,
        "z": 0.5799999999999996
    },
    "44": {
        "cost": 27.109655171871598,
        "ce": 8,
        "cc": 11,
        "z": 0.5699999999999996
    },
    "45": {
        "cost": 27.506896551174,
        "ce": 9,
        "cc": 10,
        "z": 0.5499999999999996
    },
    "46": {
        "cost": 27.550344827035197,
        "ce": 9,
        "cc": 10,
        "z": 0.5399999999999996
    },
    "47": {
        "cost": 27.5937931028964,
        "ce": 9,
        "cc": 10,
        "z": 0.5299999999999996
    },
    "48": {
        "cost": 27.6372413787576,
        "ce": 9,
        "cc": 10,
        "z": 0.5199999999999996
    },
    "49": {
        "cost": 27.6806896546188,
        "ce": 9,
        "cc": 10,
        "z": 0.5099999999999996
    },
    "50": {
        "cost": 27.692413792549598,
        "ce": 10,
        "cc": 8,
        "z": 0.4199999999999995
    },
    "51": {
        "cost": 27.72413793048,
        "ce": 9,
        "cc": 10,
        "z": 0.49999999999999956
    },
    "52": {
        "cost": 27.7675862063412,
        "ce": 9,
        "cc": 10,
        "z": 0.48999999999999955
    },
    "53": {
        "cost": 28.121379309782398,
        "ce": 10,
        "cc": 9,
        "z": 0.47999999999999954
    },
    "54": {
        "cost": 28.1648275856436,
        "ce": 10,
        "cc": 9,
        "z": 0.46999999999999953
    },
    "55": {
        "cost": 28.208275861504802,
        "ce": 10,
        "cc": 9,
        "z": 0.4599999999999995
    },
    "56": {
        "cost": 28.251724137366,
        "ce": 10,
        "cc": 9,
        "z": 0.4499999999999995
    },
    "57": {
        "cost": 28.295172413227203,
        "ce": 10,
        "cc": 9,
        "z": 0.4399999999999995
    },
    "58": {
        "cost": 28.306896551157998,
        "ce": 11,
        "cc": 7,
        "z": 0.3499999999999994
    },
    "59": {
        "cost": 28.3386206890884,
        "ce": 10,
        "cc": 9,
        "z": 0.4299999999999995
    },
    "60": {
        "cost": 28.735862068390794,
        "ce": 11,
        "cc": 8,
        "z": 0.4099999999999995
    },
    "61": {
        "cost": 28.779310344251996,
        "ce": 11,
        "cc": 8,
        "z": 0.39999999999999947
    },
    "62": {
        "cost": 28.8227586201132,
        "ce": 11,
        "cc": 8,
        "z": 0.38999999999999946
    },
    "63": {
        "cost": 28.866206895974397,
        "ce": 11,
        "cc": 8,
        "z": 0.37999999999999945
    },
    "64": {
        "cost": 28.9096551718356,
        "ce": 11,
        "cc": 8,
        "z": 0.36999999999999944
    },
    "65": {
        "cost": 28.9213793097664,
        "ce": 12,
        "cc": 6,
        "z": 0.27999999999999936
    },
    "66": {
        "cost": 28.953103447696797,
        "ce": 11,
        "cc": 8,
        "z": 0.35999999999999943
    },
    "67": {
        "cost": 29.3503448269992,
        "ce": 12,
        "cc": 7,
        "z": 0.3399999999999994
    },
    "68": {
        "cost": 29.3937931028604,
        "ce": 12,
        "cc": 7,
        "z": 0.3299999999999994
    },
    "69": {
        "cost": 29.4372413787216,
        "ce": 12,
        "cc": 7,
        "z": 0.3199999999999994
    },
    "70": {
        "cost": 29.4806896545828,
        "ce": 12,
        "cc": 7,
        "z": 0.3099999999999994
    },
    "71": {
        "cost": 29.524137930444002,
        "ce": 12,
        "cc": 7,
        "z": 0.2999999999999994
    },
    "72": {
        "cost": 29.535862068374797,
        "ce": 13,
        "cc": 5,
        "z": 0.2099999999999993
    },
    "73": {
        "cost": 29.5675862063052,
        "ce": 12,
        "cc": 7,
        "z": 0.28999999999999937
    },
    "74": {
        "cost": 29.964827585607598,
        "ce": 13,
        "cc": 6,
        "z": 0.26999999999999935
    },
    "75": {
        "cost": 29.999999999399996,
        "ce": 16,
        "cc": 0,
        "z": 0
    },
    "76": {
        "cost": 30.008275861468796,
        "ce": 13,
        "cc": 6,
        "z": 0.25999999999999934
    },
    "77": {
        "cost": 30.051724137329995,
        "ce": 13,
        "cc": 6,
        "z": 0.24999999999999933
    },
    "78": {
        "cost": 30.095172413191197,
        "ce": 13,
        "cc": 6,
        "z": 0.23999999999999932
    },
    "79": {
        "cost": 30.106896551122,
        "ce": 14,
        "cc": 4,
        "z": 0.14999999999999925
    },
    "80": {
        "cost": 30.1386206890524,
        "ce": 13,
        "cc": 6,
        "z": 0.22999999999999932
    },
    "81": {
        "cost": 30.1503448269832,
        "ce": 14,
        "cc": 4,
        "z": 0.13999999999999924
    },
    "82": {
        "cost": 30.182068964913597,
        "ce": 13,
        "cc": 6,
        "z": 0.2199999999999993
    },
    "83": {
        "cost": 30.579310344216,
        "ce": 14,
        "cc": 5,
        "z": 0.1999999999999993
    },
    "84": {
        "cost": 30.6227586200772,
        "ce": 14,
        "cc": 5,
        "z": 0.18999999999999928
    },
    "85": {
        "cost": 30.666206895938398,
        "ce": 14,
        "cc": 5,
        "z": 0.17999999999999927
    },
    "86": {
        "cost": 30.6779310338692,
        "ce": 15,
        "cc": 3,
        "z": 0.08999999999999925
    },
    "87": {
        "cost": 30.7096551717996,
        "ce": 14,
        "cc": 5,
        "z": 0.16999999999999926
    },
    "88": {
        "cost": 30.721379309730395,
        "ce": 15,
        "cc": 3,
        "z": 0.07999999999999925
    },
    "89": {
        "cost": 30.7531034476608,
        "ce": 14,
        "cc": 5,
        "z": 0.15999999999999925
    },
    "90": {
        "cost": 30.764827585591597,
        "ce": 15,
        "cc": 3,
        "z": 0.06999999999999926
    },
    "91": {
        "cost": 31.1937931028244,
        "ce": 15,
        "cc": 4,
        "z": 0.12999999999999923
    },
    "92": {
        "cost": 31.2372413786856,
        "ce": 15,
        "cc": 4,
        "z": 0.11999999999999923
    },
    "93": {
        "cost": 31.248965516616398,
        "ce": 16,
        "cc": 2,
        "z": 0.02999999999999925
    },
    "94": {
        "cost": 31.2806896545468,
        "ce": 15,
        "cc": 4,
        "z": 0.10999999999999924
    },
    "95": {
        "cost": 31.2924137924776,
        "ce": 16,
        "cc": 2,
        "z": 0.019999999999999248
    },
    "96": {
        "cost": 31.324137930408003,
        "ce": 15,
        "cc": 4,
        "z": 0.09999999999999924
    },
    "97": {
        "cost": 31.3358620683388,
        "ce": 16,
        "cc": 2,
        "z": 0.009999999999999247
    },
    "98": {
        "cost": 31.8082758614328,
        "ce": 16,
        "cc": 3,
        "z": 0.059999999999999255
    },
    "99": {
        "cost": 31.851724137294,
        "ce": 16,
        "cc": 3,
        "z": 0.04999999999999925
    },
    "100": {
        "cost": 31.895172413155198,
        "ce": 16,
        "cc": 3,
        "z": 0.03999999999999925
    }
}