{
    "0": {
        "cost": 15.862068965199999,
        "ce": 0,
        "cc": 13,
        "z": 1.0
    },
    "1": {
        "cost": 17.265517241033997,
        "ce": 2,
        "cc": 12,
        "z": 0.97
    },
    "2": {
        "cost": 17.296551723791996,
        "ce": 2,
        "cc": 12,
        "z": 0.96
    },
    "3": {
        "cost": 17.32758620655,
        "ce": 2,
        "cc": 12,
        "z": 0.95
    },
    "4": {
        "cost": 17.893103447917998,
        "ce": 2,
        "cc": 13,
        "z": 0.99
    },
    "5": {
        "cost": 17.924137930675997,
        "ce": 2,
        "cc": 13,
        "z": 0.98
    },
    "6": {
        "cost": 18.358620689287996,
        "ce": 3,
        "cc": 12,
        "z": 0.94
    },
    "7": {
        "cost": 18.389655172045998,
        "ce": 3,
        "cc": 12,
        "z": 0.9299999999999999
    },
    "8": {
        "cost": 18.420689654803997,
        "ce": 3,
        "cc": 12,
        "z": 0.9199999999999999
    },
    "9": {
        "cost": 18.451724137561996,
        "ce": 3,
        "cc": 12,
        "z": 0.9099999999999999
    },
    "10": {
        "cost": 18.48275862032,
        "ce": 3,
        "cc": 12,
        "z": 0.8999999999999999
    },
    "11": {
        "cost": 18.513793103077997,
        "ce": 3,
        "cc": 12,
        "z": 0.8899999999999999
    },
    "12": {
        "cost": 18.544827585835996,
        "ce": 3,
        "cc": 12,
        "z": 0.8799999999999999
    },
    "13": {
        "cost": 18.886206896173995,
        "ce": 4,
        "cc": 11,
        "z": 0.8699999999999999
    },
    "14": {
        "cost": 18.917241378931998,
        "ce": 4,
        "cc": 11,
        "z": 0.8599999999999999
    },
    "15": {
        "cost": 18.948275861689996,
        "ce": 4,
        "cc": 11,
        "z": 0.8499999999999999
    },
    "16": {
        "cost": 18.979310344447995,
        "ce": 4,
        "cc": 11,
        "z": 0.8399999999999999
    },
    "17": {
        "cost": 19.010344827205998,
        "ce": 4,
        "cc": 11,
        "z": 0.8299999999999998
    },
    "18": {
        "cost": 19.041379309963997,
        "ce": 4,
        "cc": 11,
        "z": 0.8199999999999998
    },
    "19": {
        "cost": 19.072413792721996,
        "ce": 4,
        "cc": 11,
        "z": 0.8099999999999998
    },
    "20": {
        "cost": 19.103448275479998,
        "ce": 4,
        "cc": 11,
        "z": 0.7999999999999998
    },
    "21": {
        "cost": 19.475862068576,
        "ce": 5,
        "cc": 10,
        "z": 0.7799999999999998
    },
    "22": {
        "cost": 19.506896551334002,
        "ce": 5,
        "cc": 10,
        "z": 0.7699999999999998
    },
    "23": {
        "cost": 19.537931034091997,
        "ce": 5,
        "cc": 10,
        "z": 0.7599999999999998
    },
    "24": {
        "cost": 19.56896551685,
        "ce": 5,
        "cc": 10,
        "z": 0.7499999999999998
    },
    "25": {
        "cost": 19.599999999608002,
        "ce": 5,
        "cc": 10,
        "z": 0.7399999999999998
    },
    "26": {
        "cost": 19.631034482365997,
        "ce": 5,
        "cc": 10,
        "z": 0.7299999999999998
    },
    "27": {
        "cost": 19.662068965124,
        "ce": 5,
        "cc": 10,
        "z": 0.7199999999999998
    },
    "28": {
        "cost": 19.693103447882,
        "ce": 5,
        "cc": 10,
        "z": 0.7099999999999997
    },
    "29": {
        "cost": 19.724137930639998,
        "ce": 5,
        "cc": 10,
        "z": 0.6999999999999997
    },
    "30": {
        "cost": 20.127586206494,
        "ce": 6,
        "cc": 9,
        "z": 0.6699999999999997
    },
    "31": {
        "cost": 20.134482758218,
        "ce": 5,
        "cc": 11,
        "z": 0.7899999999999998
    },
    "32": {
        "cost": 20.158620689252,
        "ce": 6,
        "cc": 9,
        "z": 0.6599999999999997
    },
    "33": {
        "cost": 20.18965517201,
        "ce": 6,
        "cc": 9,
        "z": 0.6499999999999997
    },
    "34": {
        "cost": 20.220689654767998,
        "ce": 6,
        "cc": 9,
        "z": 0.6399999999999997
    },
    "35": {
        "cost": 20.251724137526,
        "ce": 6,
        "cc": 9,
        "z": 0.6299999999999997
    },
    "36": {
        "cost": 20.282758620284,
        "ce": 6,
        "cc": 9,
        "z": 0.6199999999999997
    },
    "37": {
        "cost": 20.313793103042,
        "ce": 6,
        "cc": 9,
        "z": 0.6099999999999997
    },
    "38": {
        "cost": 20.717241378896,
        "ce": 7,
        "cc": 8,
        "z": 0.5799999999999996
    },
    "39": {
        "cost": 20.748275861654,
        "ce": 7,
        "cc": 8,
        "z": 0.5699999999999996
    },
    "40": {
        "cost": 20.755172413378,
        "ce": 6,
        "cc": 10,
        "z": 0.6899999999999997
    },
    "41": {
        "cost": 20.779310344411996,
        "ce": 7,
        "cc": 8,
        "z": 0.5599999999999996
    },
    "42": {
        "cost": 20.786206896135997,
        "ce": 6,
        "cc": 10,
        "z": 0.6799999999999997
    },
    "43": {
        "cost": 20.81034482717,
        "ce": 7,
        "cc": 8,
        "z": 0.5499999999999996
    },
    "44": {
        "cost": 20.841379309928,
        "ce": 7,
        "cc": 8,
        "z": 0.5399999999999996
    },
    "45": {
        "cost": 20.872413792685997,
        "ce": 7,
        "cc": 8,
        "z": 0.5299999999999996
    },
    "46": {
        "cost": 20.903448275444,
        "ce": 7,
        "cc": 8,
        "z": 0.5199999999999996
    },
    "47": {
        "cost": 20.934482758202,
        "ce": 7,
        "cc": 8,
        "z": 0.5099999999999996
    },
    "48": {
        "cost": 21.306896551298,
        "ce": 8,
        "cc": 7,
        "z": 0.48999999999999955
    },
    "49": {
        "cost": 21.337931034056,
        "ce": 8,
        "cc": 7,
        "z": 0.47999999999999954
    },
    "50": {
        "cost": 21.34482758578,
        "ce": 7,
        "cc": 9,
        "z": 0.5999999999999996
    },
    "51": {
        "cost": 21.368965516814,
        "ce": 8,
        "cc": 7,
        "z": 0.46999999999999953
    },
    "52": {
        "cost": 21.375862068537998,
        "ce": 7,
        "cc": 9,
        "z": 0.5899999999999996
    },
    "53": {
        "cost": 21.399999999572,
        "ce": 8,
        "cc": 7,
        "z": 0.4599999999999995
    },
    "54": {
        "cost": 21.43103448233,
        "ce": 8,
        "cc": 7,
        "z": 0.4499999999999995
    },
    "55": {
        "cost": 21.462068965088,
        "ce": 8,
        "cc": 7,
        "z": 0.4399999999999995
    },
    "56": {
        "cost": 21.493103447846,
        "ce": 8,
        "cc": 7,
        "z": 0.4299999999999995
    },
    "57": {
        "cost": 21.524137930604,
        "ce": 8,
        "cc": 7,
        "z": 0.4199999999999995
    },
    "58": {
        "cost": 21.927586206457995,
        "ce": 9,
        "cc": 6,
        "z": 0.38999999999999946
    },
    "59": {
        "cost": 21.958620689215998,
        "ce": 9,
        "cc": 6,
        "z": 0.37999999999999945
    },
    "60": {
        "cost": 21.965517240939995,
        "ce": 8,
        "cc": 8,
        "z": 0.49999999999999956
    },
    "61": {
        "cost": 21.989655171974,
        "ce": 9,
        "cc": 6,
        "z": 0.36999999999999944
    },
    "62": {
        "cost": 22.020689654732,
        "ce": 9,
        "cc": 6,
        "z": 0.35999999999999943
    },
    "63": {
        "cost": 22.051724137489998,
        "ce": 9,
        "cc": 6,
        "z": 0.3499999999999994
    },
    "64": {
        "cost": 22.082758620248,
        "ce": 9,
        "cc": 6,
        "z": 0.3399999999999994
    },
    "65": {
        "cost": 22.113793103006,
        "ce": 9,
        "cc": 6,
        "z": 0.3299999999999994
    },
    "66": {
        "cost": 22.51724137886,
        "ce": 10,
        "cc": 5,
        "z": 0.2999999999999994
    },
    "67": {
        "cost": 22.548275861618002,
        "ce": 10,
        "cc": 5,
        "z": 0.28999999999999937
    },
    "68": {
        "cost": 22.555172413342,
        "ce": 9,
        "cc": 7,
        "z": 0.4099999999999995
    },
    "69": {
        "cost": 22.579310344375997,
        "ce": 10,
        "cc": 5,
        "z": 0.27999999999999936
    },
    "70": {
        "cost": 22.5862068961,
        "ce": 9,
        "cc": 7,
        "z": 0.39999999999999947
    },
    "71": {
        "cost": 22.610344827134,
        "ce": 10,
        "cc": 5,
        "z": 0.26999999999999935
    },
    "72": {
        "cost": 22.641379309892002,
        "ce": 10,
        "cc": 5,
        "z": 0.25999999999999934
    },
    "73": {
        "cost": 22.672413792649998,
        "ce": 10,
        "cc": 5,
        "z": 0.24999999999999933
    },
    "74": {
        "cost": 22.703448275408,
        "ce": 10,
        "cc": 5,
        "z": 0.23999999999999932
    },
    "75": {
        "cost": 22.734482758166003,
        "ce": 10,
        "cc": 5,
        "z": 0.22999999999999932
    },
    "76": {
        "cost": 22.765517240923998,
        "ce": 10,
        "cc": 5,
        "z": 0.2199999999999993
    },
    "77": {
        "cost": 22.999999999539995,
        "ce": 13,
        "cc": 0,
        "z": 0
    },
    "78": {
        "cost": 23.106896551262,
        "ce": 11,
        "cc": 4,
        "z": 0.2099999999999993
    },
    "79": {
        "cost": 23.13793103402,
        "ce": 11,
        "cc": 4,
        "z": 0.1999999999999993
    },
    "80": {
        "cost": 23.144827585743997,
        "ce": 10,
        "cc": 6,
        "z": 0.3199999999999994
    },
    "81": {
        "cost": 23.168965516778,
        "ce": 11,
        "cc": 4,
        "z": 0.18999999999999928
    },
    "82": {
        "cost": 23.175862068501996,
        "ce": 10,
        "cc": 6,
        "z": 0.3099999999999994
    },
    "83": {
        "cost": 23.199999999536,
        "ce": 11,
        "cc": 4,
        "z": 0.17999999999999927
    },
    "84": {
        "cost": 23.22413793057,
        "ce": 12,
        "cc": 2,
        "z": 0.04999999999999925
    },
    "85": {
        "cost": 23.231034482293996,
        "ce": 11,
        "cc": 4,
        "z": 0.16999999999999926
    },
    "86": {
        "cost": 23.255172413327998,
        "ce": 12,
        "cc": 2,
        "z": 0.03999999999999925
    },
    "87": {
        "cost": 23.262068965052002,
        "ce": 11,
        "cc": 4,
        "z": 0.15999999999999925
    },
    "88": {
        "cost": 23.286206896086,
        "ce": 12,
        "cc": 2,
        "z": 0.02999999999999925
    },
    "89": {
        "cost": 23.29310344781,
        "ce": 11,
        "cc": 4,
        "z": 0.14999999999999925
    },
    "90": {
        "cost": 23.324137930567996,
        "ce": 11,
        "cc": 4,
        "z": 0.13999999999999924
    },
    "91": {
        "cost": 23.355172413326002,
        "ce": 11,
        "cc": 4,
        "z": 0.12999999999999923
    },
    "92": {
        "cost": 23.696551723664,
        "ce": 12,
        "cc": 3,
        "z": 0.11999999999999923
    },
    "93": {
        "cost": 23.727586206422,
        "ce": 12,
        "cc": 3,
        "z": 0.10999999999999924
    },
    "94": {
        "cost": 23.75862068918,
        "ce": 12,
        "cc": 3,
        "z": 0.09999999999999924
    },
    "95": {
        "cost": 23.789655171938,
        "ce": 12,
        "cc": 3,
        "z": 0.08999999999999925
    },
    "96": {
        "cost": 23.820689654696,
        "ce": 12,
        "cc": 3,
        "z": 0.07999999999999925
    },
    "97": {
        "cost": 23.851724137454,
        "ce": 12,
        "cc": 3,
        "z": 0.06999999999999926
    },
    "98": {
        "cost": 23.882758620211998,
        "ce": 12,
        "cc": 3,
        "z": 0.059999999999999255
    },
    "99": {
        "cost": 24.317241378823997,
        "ce": 13,
        "cc": 2,
        "z": 0.019999999999999248
    },
    "100": {
        "cost": 24.348275861582,
        "ce": 13,
        "cc": 2,
        "z": 0.009999999999999247
    }
}